pkcs11/__init__.py
pkcs11/_pkcs11.cpython-39-aarch64-linux-gnu.so
pkcs11/_pkcs11.pxd
pkcs11/_pkcs11.pyx
pkcs11/attributes.py
pkcs11/constants.py
pkcs11/defaults.py
pkcs11/exceptions.py
pkcs11/mechanisms.py
pkcs11/types.py
pkcs11/util/__init__.py
pkcs11/util/dh.py
pkcs11/util/dsa.py
pkcs11/util/ec.py
pkcs11/util/rsa.py
pkcs11/util/x509.py
python_pkcs11-0.9.3.dist-info/METADATA
python_pkcs11-0.9.3.dist-info/WHEEL
python_pkcs11-0.9.3.dist-info/top_level.txt
python_pkcs11-0.9.3.dist-info/RECORD
python_pkcs11-0.9.3.dist-info/licenses/LICENSE
