Metadata-Version: 2.4
Name: python-pkcs11
Version: 0.9.3
Summary: PKCS#11 support for Python
Author-email: Andrey Kislyuk <kislyuk@gmail.com>, Danielle Madeley <danielle@madeley.id.au>
Maintainer-email: Andrey Kislyuk <kislyuk@gmail.com>
License-Expression: MIT
Project-URL: Homepage, https://python-pkcs11.readthedocs.io/en/latest/
Project-URL: Documentation, https://python-pkcs11.readthedocs.io/en/latest/
Project-URL: Issues, https://github.com/pyauth/python-pkcs11/issues
Project-URL: Repository, https://github.com/pyauth/python-pkcs11
Classifier: Programming Language :: Python
Classifier: Programming Language :: Python :: 3
Classifier: Programming Language :: Python :: 3.9
Classifier: Programming Language :: Python :: 3.10
Classifier: Programming Language :: Python :: 3.11
Classifier: Programming Language :: Python :: 3.12
Classifier: Programming Language :: Python :: 3.13
Classifier: Programming Language :: Python :: 3.14
Classifier: Topic :: Security :: Cryptography
Requires-Python: >=3.9
License-File: LICENSE
Requires-Dist: asn1crypto>=1.5.1
Dynamic: license-file
